{
	"@metadata": {
		"authors": [
			"Tajamul9"
		]
	},
	"back": "واپَس",
	"button_next": "اَمہِ پتہٕ!",
	"customize": "ترتیٖب",
	"category_filter_placeholder": "موضوع کٕریٚو تلاش",
	"edits": "تَبدیٖلیہٕ",
	"in_page": "%s صفس منٛز:",
	"js-article-count": "$1 {{PLURAL:$1|مضمون|مضموٗن}}",
	"js-custom-no-articles-selected": "مہربٲنی کٔرِتھ چُنِیوٚ کینٛہہ مَضموٗن.",
	"js-keyboard-shortcut": "کی بۄرڈٕک شارٹ کٹ: %s",
	"leaderboard_link_title": "نٕتیٖجہٕ بورڈ",
	"leaderboard_title": "%s نٕتیٖجہٕ بوڈ",
	"page_not_found": "صفہٕ آونہٕ لبنہٕ!",
	"select_articles_placeholder": "مَضموٗن کھأترٕ ژھارُن",
	"submit": "دَرٕج",
	"user": "صٲرِف"
}
