{
	"@metadata": {
		"authors": [
			"Cakkaparla",
			"Tejoebāsa",
			"YaThaWinTha"
		]
	},
	"article_titles_hint": "ဂေါင်းစီးအလိုက် ဆောင်းပါးတိကို တင်သွင်း‌ရေအခါ ဂေါင်းစီးတိ မှန်ကန်ကြောင်းနန့် တစ်ကြောင်းဆိုကေ တစ်ကြောင်းစီ ပီးထားကြောင်း ပြန်စစ်ဆေးပါ။",
	"back": "နောက်သို့",
	"back_to_cancel": "မင်းစာ {em_start}{back}{em_end} ကို နှိပ်နိုင်ပါရေ မဟုတ်ကေ ဖျက်က်ဖို့ ဒေဒိုင်ယာလော့ခ်ကို ပိတ်နိုင်ရေ။",
	"button_next": "နောက်တစ်ခု",
	"button_wikilink": "ငါဒေချင့်ကိုရယာ!",
	"customize": "စိတ်ကြိုက်ပြင်ဆင်ပါ",
	"category_filter_placeholder": "အကြောင်းရာတစ်ခုကို ရှာဖွီပါ",
	"edits": "တိးဖြတ်မှုတိ",
	"footer": "%s ကို စေတနာ့ဝန်ထမ်းတိက ပြုလုပ်ထားပြီးကေ %s တွင် လက်ခံဆောင်ရွက်ပီးပြီးကေ %s ကတဆင့် ဘာသာပြန်ပါရေ။",
	"github_link_title": "သာလီစွပါ!  ငါရို့၏အရင်းအမြစ်စာGitHub တွင်ဖြစ်ရေ!",
	"import_article_titles": "ဆောင်းပါးတိဧ့ စာရင်းကို ထည့်သွင်းပါ။",
	"import_articles_prompt": "ကျေးဇူးပြပြီးကေ တင်သွင်းဖို့ ဝီကီပီးဒီးယား {em_start}ဆောင်းပါးခေါင်းစီးတိ{em_end}၊ အောက်မှာ တစ်ကြောင်းပြီးကေ တစ်ကြောင်း၊",
	"import_petscan": "PetScan မီးမြန်းမှုက တင်သွင်းပါ။",
	"import_petscan_intro": "{em_start}PetScan{em_end} စွာ ဝီကီပီးဒီးယားကို မီးမြန်းခြင်းနန့် ဆောင်းပါးစရင်းတိကို သတ်မှတ်ခြင်းအတွက် ကိရိယာတစ်ခုဖြစ်တေ။  PetScan စွာ ယင်းဧ့ရလဒတိကို အခြားကိရိယာတိတွင် ထည့်သွင်းနိုင်စီဖို့ ID တိကို စုံစမ်းမှုတိအဖြစ် သတ်မှတ်ပီးရေ။",
	"import_petscan_prompt": "ကျေးဇူးပြုပြီးကေ {link_start}PetScan တွင် သင့်မီးမြန်းချက်ကို ဖန်တီးပါ{link_end} နန့် ယင့်ဧ့ ID အောက်တွင် ကူးထည့်ပါ-",
	"in_page": "စာမျက်နှာ %s တွင်-",
	"instructions_details": "Wikipedia သို့လားရန် %s ကို နှိပ်ပြီးကေ {link_start}အတိုအထွာကို ပြင်ဆင်ပါ{link_end} ယင်းသို့မဟုတ် တခြားတစ်ခုကို ကြည့်ရန် %s။  ကံကောင်းကက်ပါစီ!",
	"instructions_goal": "အောက်ဖော်ပြရေ Wikipedia အတိုအထွာကို {link_start}ယုံကြည်စိတ်ချရရေ အရင်းအမြစ်{link_end} မှ ပံ့ပိုးမထားပါ။  တစ်ခုရှာနိုင်ဖို့လား။",
	"custom_created": "သင့်စိတ်ကြိုက် {tooltitle} ကို ဖန်တီးပြီးပါဗျာလ်။",
	"custom_end_copy_link": "မင့်က တခြားလူတိကို ယင်းကိုအသုံးပြုခွင့်ပီးဖို့ အထက်ကဖော်ပြရေ လင့်ခ်ကို ကူးယူမျှဝီနိုင်ပါရေ၊ မဟုတ်ကေ {link_start} ယင်းကိုအဂုစတင်ကြေ့ရှုပါ{link_end}။",
	"custom_failed": "ဝမ်းနည်းပါရေ၊ သင်ဧ့စိတ်ကြိုက် {tooltitle} ကို ဖန်တီးလို့မရပါ ယင်းသို့မဟုတ် ဗလာဖြစ်နီပါရေ။"
}
