{
	"@metadata": {
		"authors": [
			"Okras"
		]
	},
	"introduction": "Помогите найти источники для статей в Википедии!",
	"in_page": "На странице %s:",
	"button_wikilink": "У меня есть!",
	"button_next": "Неа, дальше!",
	"lead_section_hint": "Этот текст является частью начального раздела статьи, так что указание источников дня неё может быть необязательными. Пожалуйста, ознакомьтесь с %s для получения дополнительной информации.",
	"category_filter_placeholder": "Что именно вам интересно?",
	"github_link_title": "Эй! Мой исходный код есть на GitHub!",
	"beginners_hint": "Не знаете, как добавлять источники? См. на %s.",
	"page_not_found": "Страница не найдена!",
	"page_not_found_text": "Страницы, которую вы ищете, больше не существует. Возможно, источник для неё уже был найден? Вернитесь на %s за новыми!"
}
