{
	"@metadata": {
		"authors": [
			"AmaryllisGardener",
			"CiphriusKane"
		]
	},
	"button_next": "Next!",
	"button_wikilink": "A got this!",
	"category_filter_placeholder": "Sairch for a topic",
	"footer": "%s is made bi volunteers, hostit on %s an translatit via %s.",
	"github_link_title": "Hey! Ma soorce is on GitHub!",
	"in_page": "In page %s:",
	"instructions_details": "Sneck on %s tae gang tae Wikipaedia an {link_start}fix the snippet{link_end}, or %s tae see anither ane. Guid luck!",
	"instructions_goal": "The Wikipaedia snippet ablo isna backed bi a {link_start}reliable source{link_end}. Can ye find ane?",
	"introduction": "Help find citations for Wikipaedia airticles!",
	"js-article-count": "$1 {{PLURAL:$1|airticle|airticles}}",
	"js-keyboard-shortcut": "Keybuird shortcut: %s",
	"js-refs-added-today": "$1 {{PLURAL:$1|citation|citations}} addit the day!",
	"lead_section_hint": "This text is pairt o the airticle's lead section, sae referencin it mey be optional. Please see %s for mair information.",
	"page_not_found": "Page nae foond!",
	"page_not_found_text": "The page that ye'r luikin fur nae langer exists — aiblins this citation haes aareidy been fand? Gang back tae %s fur mair!"
}
